{"episode":"Season 1, Episode 9","name":"The Well-Tempered Clavier","aire_date":"November 27, 2016"}
{"episode":"Season 1, Episode 8","name":"Trace Decay","aire_date":"November 20, 2016"}
{"episode":"Season 1, Episode 7","name":"Trompe L&#39;Oeil","aire_date":"November 13, 2016"}
{"episode":"Season 1, Episode 6","name":"The Adversary","aire_date":"November 6, 2016"}
{"episode":"Season 1, Episode 5","name":"Contrapasso","aire_date":"October 30, 2016"}
{"episode":"Season 1, Episode 4","name":"Dissonance Theory","aire_date":"October 23, 2016"}
{"episode":"Season 1, Episode 3","name":"The Stray","aire_date":"October 16, 2016"}
{"episode":"Season 1, Episode 2","name":"Chestnut","aire_date":"October 9, 2016"}
{"episode":"Season 1, Episode 1","name":"The Original","aire_date":"October 2, 2016"}
